[
  {
    "id": "1",
    "title": "Bring The Rock Back To Rome",
    "tagline": "Presented by 3rd Shift Evetns",
    "location": "1188 Erie Blvd W, Rome, NY 13440",
    "time": "7pm - 11pm",
    "date": "Sept 24th, 2022",
    "description": "",
    "price": "$10",
    "logo": "assets/images/companies/company-1.png",
    "href": "https://www.3rdshiftgroup.com/event-details/bring-the-rock-back-to-rome"
  },
  {
    "id": "2",
    "title": "Barbie VS Bratz Party",
    "tagline": "Hosted by Deluzional Desserts",
    "location": "1188 Erie Blvd W, Rome, NY 13440",
    "time": "8pm - 11:50pm",
    "date": "Feb 1st, 2022",
    "description": "",
    "price": "$30",
    "logo": "assets/images/companies/company-1.png",
    "href": "https://www.3rdshiftgroup.com/event-details/barbie-vs-bratz-party-hosted-by-deluzional-desserts"
  }

  
]
